MANIFEST.in
README.md
setup.cfg
setup.py
masnet/__init__.py
masnet/analyze.py
masnet/default_exclusion_patterns
masnet/download.py
masnet/generate.py
masnet.egg-info/PKG-INFO
masnet.egg-info/SOURCES.txt
masnet.egg-info/dependency_links.txt
masnet.egg-info/entry_points.txt
masnet.egg-info/not-zip-safe
masnet.egg-info/requires.txt
masnet.egg-info/top_level.txt