Metadata-Version: 2.1
Name: masnet
Version: 0.3.4
Summary: tools for Mastodon network analysis
Home-page: https://github.com/metebalci/masnet
Author: Mete Balci
Author-email: metebalci@gmail.com
License: GPLv3
Keywords: Mastodon
Platform: UNKNOWN
Classifier: Development Status :: 3 - Alpha
Classifier: Environment :: Console
Classifier: Intended Audience :: Science/Research
Classifier: License :: OSI Approved :: GNU General Public License v3 (GPLv3)
Classifier: Natural Language :: English
Classifier: Operating System :: OS Independent
Classifier: Programming Language :: Python :: 3 :: Only
Classifier: Topic :: Scientific/Engineering
Classifier: Topic :: Scientific/Engineering :: Information Analysis
Classifier: Topic :: Scientific/Engineering :: Visualization
Classifier: Topic :: Utilities
